.hgignore
.hgtags
.project
setup.py
django_hierarchy.egg-info/PKG-INFO
django_hierarchy.egg-info/SOURCES.txt
django_hierarchy.egg-info/dependency_links.txt
django_hierarchy.egg-info/requires.txt
django_hierarchy.egg-info/top_level.txt
src/__init__.py
src/__version__.py
src/html_tree.py
src/model_tree.py
src/models.py
src/test_tree.py
src/tree.py