Metadata-Version: 1.0
Name: django-hierarchy
Version: 0.2.1
Summary: A library for storing trees in the Django ORM.
Home-page: http://bitbucket.org/lars512/django-hierarchy/
Author: Lars Yencken
Author-email: lljy@csse.unimelb.edu.au
License: BSD
Platform: UNKNOWN
